README.md
setup.py
12306_booking.egg-info/PKG-INFO
12306_booking.egg-info/SOURCES.txt
12306_booking.egg-info/dependency_links.txt
12306_booking.egg-info/entry_points.txt
12306_booking.egg-info/requires.txt
12306_booking.egg-info/top_level.txt
booking/__init__.py
booking/_logging.py
booking/auth.py
booking/command.py
booking/exceptions.py
booking/login.wav
booking/order.py
booking/pay.py
booking/query.py
booking/remind.py
booking/run.py
booking/settings.py
booking/station_list.json
booking/train.mp3
booking/user.py
booking/utils.py